{
  "identifier": "3aff94d4-d619-4f30-9644-5ab0fff05999",
  "type": "dcat:Dataset",
  "title": "List Species",
  "description": "1",
  "resources": [
    {
      "name": "distribution_1",
      "schema": {
        "fields": [
          {
            "name": "dummy_field"
          }
        ]
      },
      "header_count": 1,
      "dummy_content": [
        {
          "dummy_field": 1
        }
      ]
    },
    {
      "name": "distribution_2",
      "schema": {
        "fields": [
          {
            "name": "dummy_field"
          }
        ]
      },
      "header_count": 1,
      "dummy_content": [
        {
          "dummy_field": 1
        }
      ]
    }
  ],
  "levels": {
    "title": 1,
    "description": 1,
    "headers": 1,
    "content": 1
  }
}