{
  "identifier": "sample-ffee7fd5-d868-49ab-9ff4-ed9a846235db",
  "type": "cbm:Sample",
  "title": "List Species",
  "description": "1",
  "isSampleOf": "ffee7fd5-d868-49ab-9ff4-ed9a846235db",
  "resources": [
    {
      "name": "distribution_1",
      "schema": {
        "fields": [
          {
            "name": "dummy_field"
          }
        ]
      },
      "header_count": 1,
      "dummy_content": [
        {
          "dummy_field": 1
        }
      ]
    },
    {
      "name": "distribution_2",
      "schema": {
        "fields": [
          {
            "name": "dummy_field"
          }
        ]
      },
      "header_count": 1,
      "dummy_content": [
        {
          "dummy_field": 1
        }
      ]
    }
  ],
  "levels": {
    "title": 1,
    "description": 1,
    "headers": 1,
    "content": 1
  }
}